Metadata-Version: 2.1
Name: funes
Version: 0.0.1
Summary: Decorator to memorize function computations permanently to disk.
Home-page: https://github.com/taliesinb/funes
Author: Taliesin Beynon
Author-email: contact@taliesin.ai
License: MIT
Download-URL: https://github.com/taliesinb/funes/archive/v0.0.1.tar.gz
Keywords: persistent,cache,hash,stable,archive,memoize
Platform: UNKNOWN
Classifier: License :: OSI Approved :: MIT License
Classifier: Programming Language :: Python :: 3
Classifier: Programming Language :: Python :: 3.7
